MANIFEST.in
README
setup.py
pelicanfly/__init__.py
pelicanfly/pelicanfly.py
pelicanfly.egg-info/PKG-INFO
pelicanfly.egg-info/SOURCES.txt
pelicanfly.egg-info/dependency_links.txt
pelicanfly.egg-info/not-zip-safe
pelicanfly.egg-info/requires.txt
pelicanfly.egg-info/top_level.txt
pelicanfly/static/css/font-awesome.css
pelicanfly/static/css/font-awesome.css.map
pelicanfly/static/css/font-awesome.min.css
pelicanfly/static/fonts/FontAwesome.otf
pelicanfly/static/fonts/fontawesome-webfont.eot
pelicanfly/static/fonts/fontawesome-webfont.svg
pelicanfly/static/fonts/fontawesome-webfont.ttf
pelicanfly/static/fonts/fontawesome-webfont.woff
pelicanfly/static/fonts/fontawesome-webfont.woff2