Metadata-Version: 1.0
Name: pelicanfly
Version: 0.4.4
Summary: Font Awesome from inside a Pelican
Home-page: http://bmcorser.github.com/pelicanfly
Author: bmcorser
Author-email: benmarshallcorser@gmail.com
License: GPL
Platform: UNKNOWN
